pgq/__init__.py
pgq/baseconsumer.py
pgq/consumer.py
pgq/coopconsumer.py
pgq/event.py
pgq/localconsumer.py
pgq/producer.py
pgq/py.typed
pgq/remoteconsumer.py
pgq/status.py
pgq/cascade/__init__.py
pgq/cascade/admin.py
pgq/cascade/consumer.py
pgq/cascade/nodeinfo.py
pgq/cascade/worker.py
pgq-3.8.dist-info/METADATA
pgq-3.8.dist-info/WHEEL
pgq-3.8.dist-info/top_level.txt
pgq-3.8.dist-info/RECORD
